AUTHORS
LICENSE.txt
MANIFEST.in
README.rst
setup.py
tests/__init__.py
tests/test_config.py
tests/exchange/__init__.py
tests/exchange/test_action.py
tests/exchange/test_candle_sticks.py
tests/exchange/test_currency_pairs.py
tests/exchange/test_period.py
tests/exchange/test_tick.py
tests/rules/__init__.py
tests/rules/test_entry.py
tests/rules/test_exit.py
tests/trade/__init__.py
tests/trade/test_strategy.py
tests/trade/test_trade.py
zaifbot/__init__.py
zaifbot/config.py
zaifbot/errors.py
zaifbot/logger.py
zaifbot/notifyer.py
zaifbot.egg-info/PKG-INFO
zaifbot.egg-info/SOURCES.txt
zaifbot.egg-info/dependency_links.txt
zaifbot.egg-info/entry_points.txt
zaifbot.egg-info/requires.txt
zaifbot.egg-info/top_level.txt
zaifbot/analysis/__init__.py
zaifbot/analysis/trade_result.py
zaifbot/db/__init__.py
zaifbot/db/config.py
zaifbot/db/seed.py
zaifbot/db/dao/__init__.py
zaifbot/db/dao/base.py
zaifbot/db/dao/candle_sticks.py
zaifbot/db/dao/trades.py
zaifbot/exchange/__init__.py
zaifbot/exchange/action.py
zaifbot/exchange/candle_sticks.py
zaifbot/exchange/currency_pairs.py
zaifbot/exchange/latest_price.py
zaifbot/exchange/period.py
zaifbot/exchange/tick.py
zaifbot/exchange/api/__init__.py
zaifbot/exchange/api/http.py
zaifbot/exchange/api/websocket.py
zaifbot/indicators/__init__.py
zaifbot/indicators/adx.py
zaifbot/indicators/bollinger_bands.py
zaifbot/indicators/indicator.py
zaifbot/indicators/macd.py
zaifbot/indicators/moving_average.py
zaifbot/indicators/rsi.py
zaifbot/logs/.keep
zaifbot/logs/trades/.keep
zaifbot/rules/__init__.py
zaifbot/rules/rule.py
zaifbot/rules/entry/__init__.py
zaifbot/rules/entry/always_true_entry.py
zaifbot/rules/entry/base.py
zaifbot/rules/entry/buy_lower_entry.py
zaifbot/rules/entry/sell_higher_entry.py
zaifbot/rules/exit/__init__.py
zaifbot/rules/exit/always_false_exit.py
zaifbot/rules/exit/always_true_exit.py
zaifbot/rules/exit/base.py
zaifbot/rules/exit/buy_lower_exit.py
zaifbot/rules/exit/sell_higher_exit.py
zaifbot/rules/stop/__init__.py
zaifbot/rules/stop/base.py
zaifbot/setup/TA_Lib-0.4.10-cp34-cp34m-win32.whl
zaifbot/setup/TA_Lib-0.4.10-cp34-cp34m-win_amd64.whl
zaifbot/setup/TA_Lib-0.4.10-cp35-cp35m-win32.whl
