Metadata-Version: 1.1
Name: zaifbot
Version: 0.0.8
Summary: trading bot framework for zaif exchange
Home-page: https://github.com/techbureau/zaifbot
Author: AkiraTaniguchi DaikiShiroi Monji
Author-email: a.taniguchi@techbureau.jp daikishiroi@gmail.com
License: MIT
Keywords: zaif bit coin btc xem mona jpy virtual currency block chain bot
Platform: UNKNOWN
Classifier: Programming Language :: Python
Classifier: Development Status :: 4 - Beta
Classifier: Programming Language :: Python :: 3.4
Classifier: Programming Language :: Python :: 3.5
Classifier: Programming Language :: Python :: 3.6
Classifier: Programming Language :: Python :: 3 :: Only
Classifier: Intended Audience :: Developers
Classifier: License :: OSI Approved :: MIT License
